{
"type": "FeatureCollection",
"name": "weltkriegsdenkmal",
"crs": { "type": "name", "properties": { "name": "urn:ogc:def:crs:OGC:1.3:CRS84" } },
"features": [
{ "type": "Feature", "properties": { }, "geometry": { "type": "Point", "coordinates": [ 13.047404576216683, 47.778445846942752, 0.0 ] } }
]
}
